Workbook

Sheet Summary
A1: Paso Competitive Scan
A2: Team Assignment 5. HaYoung Kong, Samuel Quansah, Martin Sosa, Benjamin Karp. Competitor facts accessed 2026-10-05.
A4: Product | B4: Type | C4: Features (of 36) | D4: Benefits (of 36) | E4: Features no one else has
A5: Paso (planned MVP) | B5: Our venture (planned MVP) | C5: ='Features & Benefits Matrix'!D50 -> 27 | D5: ='Features & Benefits Matrix'!D97 -> 27 | E5: =COUNTIFS('Features & Benefits Matrix'!D7:D49,"x",'Features & Benefits Matrix'!K7:K49,1) -> 3
A6: WES | B6: Direct: records | C6: ='Features & Benefits Matrix'!E50 -> 10 | D6: ='Features & Benefits Matrix'!E97 -> 10 | E6: =COUNTIFS('Features & Benefits Matrix'!E7:E49,"x",'Features & Benefits Matrix'!K7:K49,1) -> 0
A7: ECE | B7: Direct: records | C7: ='Features & Benefits Matrix'!F50 -> 14 | D7: ='Features & Benefits Matrix'!F97 -> 14 | E7: =COUNTIFS('Features & Benefits Matrix'!F7:F49,"x",'Features & Benefits Matrix'!K7:K49,1) -> 0
A8: i-Ready | B8: Indirect: skills | C8: ='Features & Benefits Matrix'!G50 -> 12 | D8: ='Features & Benefits Matrix'!G97 -> 12 | E8: =COUNTIFS('Features & Benefits Matrix'!G7:G49,"x",'Features & Benefits Matrix'!K7:K49,1) -> 1
A9: Ellevation | B9: Indirect: district EL platform | C9: ='Features & Benefits Matrix'!H50 -> 11 | D9: ='Features & Benefits Matrix'!H97 -> 11 | E9: =COUNTIFS('Features & Benefits Matrix'!H7:H49,"x",'Features & Benefits Matrix'!K7:K49,1) -> 1
A10: TalkingPoints | B10: Indirect: family messaging | C10: ='Features & Benefits Matrix'!I50 -> 10 | D10: ='Features & Benefits Matrix'!I97 -> 10 | E10: =COUNTIFS('Features & Benefits Matrix'!I7:I49,"x",'Features & Benefits Matrix'!K7:K49,1) -> 2
A11: Status quo (baseline) | B11: Baseline (not a competitor) | C11: ='Features & Benefits Matrix'!J50 -> 1 | D11: ='Features & Benefits Matrix'!J97 -> 1 | E11: =COUNTIFS('Features & Benefits Matrix'!J7:J49,"x",'Features & Benefits Matrix'!K7:K49,1) -> 0
A13: Paso's column shows planned MVP features, not a live product. Paso figures are targets and hypotheses.
A15: Trends
A16: What categories of features and benefits do you notice?
A17: ="Eight categories emerge, and the field splits into three camps. Credential evaluators cluster in record capture and course mapping (WES "&(COUNTIF('Features & Benefits Matrix'!E7:E11,"x")+COUNTIF('Features & Benefits Matrix'!E13:E16,"x"))&", ECE "&(COUNTIF('Features & Benefits Matrix'!F7:F11,"x")+COUNTIF('Features & Benefits Matrix'!F13:F16,"x"))&" of 9 features); "&"i-Ready and Ellevation cluster in skills and decision support ("&(COUNTIF('Features & Benefits Matrix'!G18:G21,"x")+COUNTIF('Features & Benefits Matrix'!G23:G26,"x"))&" and "&(COUNTIF('Features & Benefits Matrix'!H18:H21,"x")+COUNTIF('Features & Benefits Matrix'!H23:H26,"x"))&" of 8); TalkingPoints owns family communication ("&(COUNTIF('Features & Benefits Matrix'!I28:I33,"x"))&" of 6). "&"Benefits follow the same split: trusted equivalency, classroom instruction and compliance, and family reach." -> Eight categories emerge, and the field splits into three camps. Credential evaluators cluster in record capture and course mapping (WES 6, ECE 7 of 9 features); i-Ready and Ellevation cluster in skills and decision support (6 and 4 of 8); TalkingPoints owns family communication (5 of 6). Benefits follow the same split: trusted equivalency, classroom instruction and compliance, and family reach.
A19: How do Paso's features and benefits compare with competitors'?
A20: ="Paso's planned MVP marks "&C5&" of 36 features; the closest competitor, "&INDEX(A6:A10,MATCH(MAX(C6:C10),C6:C10,0))&", marks "&MAX(C6:C10)&". "&"Paso alone plans "&E5&" of them, led by one recommendation that combines records with a skills check and a match to local grade level and courses. "&"Paso deliberately leaves out document authentication, adaptive testing, lessons and district sales." -> Paso's planned MVP marks 27 of 36 features; the closest competitor, ECE, marks 14. Paso alone plans 3 of them, led by one recommendation that combines records with a skills check and a match to local grade level and courses. Paso deliberately leaves out document authentication, adaptive testing, lessons and district sales.
A22: Who are your main competitors? What are your differentiators?
A23: Main competitors are WES and ECE, which evaluate foreign records and both run refugee programs (WES Gateway, ECE Aid), and i-Ready, which schools use to find a student's level; Ellevation and TalkingPoints hold the district and family channels. Paso's differentiators: (1) every recommendation carries its proof: course-to-credit mapping, skills-check results and a reviewer's sign-off; (2) a local grade and course plan, not only a U.S. equivalency; (3) sold to resettlement nonprofits, and families never pay.
A25: Positioning statement
A26: For resettlement nonprofits enrolling newcomer teens, who wait weeks to place students because foreign records are hard to read and a wrong placement is costly, Paso is a starting-point planning service that turns photos of school records into a defensible plan (grade, courses, credits and next steps) in three business days (target), in the family's language. Unlike credential evaluators such as WES and ECE, Paso combines the record with a short skills check and matches it to local courses, not only to a U.S. equivalency.
A28: AI use
A29: We used Claude (Anthropic) to structure the competitive scan, check competitor features against their websites and format the workbook; the team selected the competitors, verified the findings and approved all content.

Sheet Paso MVP
A1: Paso MVP: features and benefits
A2: Step 1. What the minimum viable product does, how the team runs it by hand now, and who benefits. Targets are hypotheses, not results.
A4: # | B4: Feature | C4: MVP (how we'll support it now) | D4: Benefit to the customer | E4: Curve-jumping
A5: 1 | B5: Capture records by phone | C5: A case manager or family sends photos of report cards and transcripts by WhatsApp or a Google Form; a team member opens the case in a shared tracker. | D5: Case manager: starts a case the day records arrive, with whatever documents the family has, and no sealed envelopes or mailing.
A6: 2 | B6: Read and translate records | C6: A team member uses Claude to read each photo and translate course names and grades into a template; a bilingual reviewer checks every line. | D6: Case manager: replaces "informal Google searches or unstandardized translation tools" (team interview). Target: prep time from about 4 to 2 staff hours per student.
A7: 3 | B7: Map courses to local credits | C7: A shared Google Sheet matches each prior course to a local course and credit, and notes the evidence for each match. | D7: Student: gets credit for courses already passed instead of repeating them. School: sees the reasoning behind each credit.
A8: 4 | B8: Check skills in 30 minutes | C8: A fixed paper check (reading, math with numbers and pictures, and a short English task) given at the affiliate office with an adult present and instructions in the student's language; scored with a rubric. | D8: Student: placed by what they can do now, even when records are missing or unclear.
A9: 5 | B9: Sign off an evidence-backed plan | C9: A Google Docs plan template (grade, courses, credits, next steps) where every line cites its evidence; a trained reviewer completes a checklist and signs before release. | D9: Case manager: can stand behind a recommendation and move it forward. The interview found that "fear of placing a student in the wrong grade level causes staff to delay recommendations while they wait for school district responses." | E9: Yes
A10: 6 | B10: Share the plan in the family's language | C10: A one-page family plan, about a 6th-grade reading level, translated and checked by a native speaker (Spanish and Arabic first), sent by WhatsApp or printed and walked through by the case manager. | D10: Family: understands where the student starts and what to ask the school (tests H1).
A11: 7 | B11: Send a standard school letter | C11: A Google Docs letter template filled from the plan and sent by the case manager. | D11: Case manager: ends letters drafted "from scratch for every case" (team interview). School: receives the same clear format every time.
A12: 8 | B12: Track every case | C12: A Google Sheet logs intake date, plan date and staff minutes for each case. | D12: Affiliate: shows funders turnaround and time saved. Target: about 2 weeks to 3 business days (tests H2).
A13: 9 | B13: Protect family data | C13: Collect only school records and contact details, never immigration status; named team members only; signed consent; pilot data deleted on a set date. | D13: Family and affiliate: can trust Paso with a vulnerable group's records.
B15: Why the evidence-backed plan is curve-jumping
B16: Today a newcomer's starting point comes from a credential evaluation built for colleges and employers (official documents, weeks of waiting) or from a case manager's best guess. Paso jumps to a new curve by attaching proof to every recommendation: a course-to-credit mapping, skills-check results and a reviewer's sign-off, so staff can act the same week instead of waiting.
B18: MVP experience in 5 steps
B19: Step | C19: What happens | D19: One action
B20: 1. Upload | C20: The case manager sends photos of the student's records. | D20: Send photos
B21: 2. Read | C21: Paso translates every record and maps each course to a local course and credit. | D21: Confirm the student's details
B22: 3. Check | C22: The student takes the 30-minute skills check with an adult present. | D22: Start the check
B23: 4. Review | C23: A trained reviewer checks the evidence and signs the plan. | D23: Approve
B24: 5. Plan delivered | C24: By day 3 (target), the family gets a one-page plan in their language at about a 6th-grade reading level, and the school gets a standard letter. | D24: Share the plan
B26: Not in the MVP
B27: Official placement decisions | C27: Schools decide; Paso recommends.
B28: AI-only plans | C28: Every plan carries a trained reviewer's sign-off.
B29: Document authentication | C29: Paso records where each document came from; a school or evaluator can authenticate when needed.
B30: District sales and SIS integration | C30: Districts are phase two, after the nonprofit workflow and demand are validated.
B31: A custom app or lesson content | C31: WhatsApp, forms and documents are enough to test the core job.

Sheet Features & Benefits Matrix
A1: Features & Benefits Matrix
A2: x = offered (competitors: verified on their own website, see Sources; Paso: planned MVP). Blank = not offered or not verified. Hover a cell's red corner for its source.
A4: # | B4: Category | C4: Feature / Benefit | D4: Paso (planned MVP) | E4: WES | F4: ECE | G4: i-Ready | H4: Ellevation | I4: TalkingPoints | J4: Status quo (baseline) | K4: Total (of 7)
A5: FEATURES
B6: Record capture & translation
A7: F1 | B7: Record capture & translation | C7: Receive records digitally | D7: x | E7: x | F7: x | K7: =COUNTIF(D7:J7,"x") -> 3
A8: F2 | B8: Record capture & translation | C8: Accept copies when official records are missing | D8: x | E8: x | K8: =COUNTIF(D8:J8,"x") -> 2
A9: F3 | B9: Record capture & translation | C9: Translate records into English | D9: x | F9: x | J9: x | K9: =COUNTIF(D9:J9,"x") -> 3
A10: F4 | B10: Record capture & translation | C10: Read transcripts with AI | D10: x | F10: x | K10: =COUNTIF(D10:J10,"x") -> 2
A11: F5 | B11: Record capture & translation | C11: Verify authenticity with the issuing school | E11: x | F11: x | K11: =COUNTIF(D11:J11,"x") -> 2
B12: Course & credit mapping
A13: F6 | B13: Course & credit mapping | C13: Evaluate secondary-school records | D13: x | E13: x | F13: x | K13: =COUNTIF(D13:J13,"x") -> 3
A14: F7 | B14: Course & credit mapping | C14: Evaluate course by course | D14: x | E14: x | F14: x | K14: =COUNTIF(D14:J14,"x") -> 3
A15: F8 | B15: Course & credit mapping | C15: Convert grades and credits to U.S. terms | D15: x | E15: x | F15: x | K15: =COUNTIF(D15:J15,"x") -> 3
A16: F9 | B16: Course & credit mapping | C16: Match to local grade level and courses | D16: x | K16: =COUNTIF(D16:J16,"x") -> 1
B17: Skills assessment
A18: F10 | B18: Skills assessment | C18: Assess reading and math | D18: x | G18: x | K18: =COUNTIF(D18:J18,"x") -> 2
A19: F11 | B19: Skills assessment | C19: Adapt questions to each student | G19: x | K19: =COUNTIF(D19:J19,"x") -> 1
A20: F12 | B20: Skills assessment | C20: Test in the student's home language | D20: x | G20: x | K20: =COUNTIF(D20:J20,"x") -> 2
A21: F13 | B21: Skills assessment | C21: Measure English proficiency | D21: x | H21: x | K21: =COUNTIF(D21:J21,"x") -> 2
B22: Recommendation & decision support
A23: F14 | B23: Recommendation & decision support | C23: Recommend a starting point | D23: x | G23: x | H23: x | K23: =COUNTIF(D23:J23,"x") -> 3
A24: F15 | B24: Recommendation & decision support | C24: Combine records and skills results in one recommendation | D24: x | K24: =COUNTIF(D24:J24,"x") -> 1
A25: F16 | B25: Recommendation & decision support | C25: Suggest next instructional steps | D25: x | G25: x | H25: x | K25: =COUNTIF(D25:J25,"x") -> 3
A26: F17 | B26: Recommendation & decision support | C26: Provide lessons or classroom activities | G26: x | H26: x | K26: =COUNTIF(D26:J26,"x") -> 2
B27: Family communication
A28: F18 | B28: Family communication | C28: Give families a plain-language report | D28: x | G28: x | K28: =COUNTIF(D28:J28,"x") -> 2
A29: F19 | B29: Family communication | C29: Communicate in the family's language | D29: x | G29: x | H29: x | I29: x | K29: =COUNTIF(D29:J29,"x") -> 4
A30: F20 | B30: Family communication | C30: Send two-way translated messages | I30: x | K30: =COUNTIF(D30:J30,"x") -> 1
A31: F21 | B31: Family communication | C31: Reach families without a new app | D31: x | I31: x | K31: =COUNTIF(D31:J31,"x") -> 2
A32: F22 | B32: Family communication | C32: Help families support learning at home | G32: x | I32: x | K32: =COUNTIF(D32:J32,"x") -> 2
A33: F23 | B33: Family communication | C33: Flag families who aren't being reached | I33: x | K33: =COUNTIF(D33:J33,"x") -> 1
B34: Case workflow & reporting
A35: F24 | B35: Case workflow & reporting | C35: Use a standard report or letter | D35: x | E35: x | F35: x | K35: =COUNTIF(D35:J35,"x") -> 3
A36: F25 | B36: Case workflow & reporting | C36: Track each case online | D36: x | F36: x | H36: x | K36: =COUNTIF(D36:J36,"x") -> 3
A37: F26 | B37: Case workflow & reporting | C37: See program dashboards and reports | D37: x | G37: x | H37: x | I37: x | K37: =COUNTIF(D37:J37,"x") -> 4
A38: F27 | B38: Case workflow & reporting | C38: Produce compliance reports | H38: x | K38: =COUNTIF(D38:J38,"x") -> 1
A39: F28 | B39: Case workflow & reporting | C39: Sync with student information systems | H39: x | I39: x | K39: =COUNTIF(D39:J39,"x") -> 2
A40: F29 | B40: Case workflow & reporting | C40: Return results within one week | D40: x | F40: x | K40: =COUNTIF(D40:J40,"x") -> 2
B41: Trust, privacy & human review
A42: F30 | B42: Trust, privacy & human review | C42: Have a trained person review every result | D42: x | E42: x | F42: x | K42: =COUNTIF(D42:J42,"x") -> 3
A43: F31 | B43: Trust, privacy & human review | C43: Publish student-data privacy commitments | D43: x | G43: x | H43: x | I43: x | K43: =COUNTIF(D43:J43,"x") -> 4
A44: F32 | B44: Trust, privacy & human review | C44: Serve refugees and displaced people | D44: x | E44: x | F44: x | K44: =COUNTIF(D44:J44,"x") -> 3
B45: Access & pricing
A46: F33 | B46: Access & pricing | C46: Publish prices | D46: x | E46: x | F46: x | K46: =COUNTIF(D46:J46,"x") -> 3
A47: F34 | B47: Access & pricing | C47: Free for families | D47: x | F47: x | I47: x | K47: =COUNTIF(D47:J47,"x") -> 3
A48: F35 | B48: Access & pricing | C48: Sold to resettlement nonprofits | D48: x | K48: =COUNTIF(D48:J48,"x") -> 1
A49: F36 | B49: Access & pricing | C49: Sold to schools and districts | G49: x | H49: x | I49: x | K49: =COUNTIF(D49:J49,"x") -> 3
C50: Features total (of 36) | D50: =COUNTIF(D7:D49,"x") -> 27 | E50: =COUNTIF(E7:E49,"x") -> 10 | F50: =COUNTIF(F7:F49,"x") -> 14 | G50: =COUNTIF(G7:G49,"x") -> 12 | H50: =COUNTIF(H7:H49,"x") -> 11 | I50: =COUNTIF(I7:I49,"x") -> 10 | J50: =COUNTIF(J7:J49,"x") -> 1
A52: BENEFITS (each benefit B# comes from feature F# with the same number)
B53: Record capture & translation
A54: B1 | B54: Record capture & translation | C54: Cases start the day records arrive, with no mailing or sealed envelopes | D54: =IF(D7="x","x","") -> x | E54: =IF(E7="x","x","") -> x | F54: =IF(F7="x","x","") -> x | G54: =IF(G7="x","x","") | H54: =IF(H7="x","x","") | I54: =IF(I7="x","x","") | J54: =IF(J7="x","x","") | K54: =COUNTIF(D54:J54,"x") -> 3
A55: B2 | B55: Record capture & translation | C55: Students without official documents can still be evaluated | D55: =IF(D8="x","x","") -> x | E55: =IF(E8="x","x","") -> x | F55: =IF(F8="x","x","") | G55: =IF(G8="x","x","") | H55: =IF(H8="x","x","") | I55: =IF(I8="x","x","") | J55: =IF(J8="x","x","") | K55: =COUNTIF(D55:J55,"x") -> 2
A56: B3 | B56: Record capture & translation | C56: Staff don't need to find or pay a separate translator | D56: =IF(D9="x","x","") -> x | E56: =IF(E9="x","x","") | F56: =IF(F9="x","x","") -> x | G56: =IF(G9="x","x","") | H56: =IF(H9="x","x","") | I56: =IF(I9="x","x","") | J56: =IF(J9="x","x","") -> x | K56: =COUNTIF(D56:J56,"x") -> 3
A57: B4 | B57: Record capture & translation | C57: Course data is pulled out in minutes, whatever the format or language | D57: =IF(D10="x","x","") -> x | E57: =IF(E10="x","x","") | F57: =IF(F10="x","x","") -> x | G57: =IF(G10="x","x","") | H57: =IF(H10="x","x","") | I57: =IF(I10="x","x","") | J57: =IF(J10="x","x","") | K57: =COUNTIF(D57:J57,"x") -> 2
A58: B5 | B58: Record capture & translation | C58: Receivers can trust the documents are genuine | D58: =IF(D11="x","x","") | E58: =IF(E11="x","x","") -> x | F58: =IF(F11="x","x","") -> x | G58: =IF(G11="x","x","") | H58: =IF(H11="x","x","") | I58: =IF(I11="x","x","") | J58: =IF(J11="x","x","") | K58: =COUNTIF(D58:J58,"x") -> 2
B59: Course & credit mapping
A60: B6 | B60: Course & credit mapping | C60: Middle- and high-school learning is recognized, not only degrees | D60: =IF(D13="x","x","") -> x | E60: =IF(E13="x","x","") -> x | F60: =IF(F13="x","x","") -> x | G60: =IF(G13="x","x","") | H60: =IF(H13="x","x","") | I60: =IF(I13="x","x","") | J60: =IF(J13="x","x","") | K60: =COUNTIF(D60:J60,"x") -> 3
A61: B7 | B61: Course & credit mapping | C61: Each prior course can count toward a requirement | D61: =IF(D14="x","x","") -> x | E61: =IF(E14="x","x","") -> x | F61: =IF(F14="x","x","") -> x | G61: =IF(G14="x","x","") | H61: =IF(H14="x","x","") | I61: =IF(I14="x","x","") | J61: =IF(J14="x","x","") | K61: =COUNTIF(D61:J61,"x") -> 3
A62: B8 | B62: Course & credit mapping | C62: Schools read prior grades and credits on a familiar scale | D62: =IF(D15="x","x","") -> x | E62: =IF(E15="x","x","") -> x | F62: =IF(F15="x","x","") -> x | G62: =IF(G15="x","x","") | H62: =IF(H15="x","x","") | I62: =IF(I15="x","x","") | J62: =IF(J15="x","x","") | K62: =COUNTIF(D62:J62,"x") -> 3
A63: B9 | B63: Course & credit mapping | C63: Students get credit for what they've done and repeat fewer courses | D63: =IF(D16="x","x","") -> x | E63: =IF(E16="x","x","") | F63: =IF(F16="x","x","") | G63: =IF(G16="x","x","") | H63: =IF(H16="x","x","") | I63: =IF(I16="x","x","") | J63: =IF(J16="x","x","") | K63: =COUNTIF(D63:J63,"x") -> 1
B64: Skills assessment
A65: B10 | B65: Skills assessment | C65: Placement reflects what the student can do now | D65: =IF(D18="x","x","") -> x | E65: =IF(E18="x","x","") | F65: =IF(F18="x","x","") | G65: =IF(G18="x","x","") -> x | H65: =IF(H18="x","x","") | I65: =IF(I18="x","x","") | J65: =IF(J18="x","x","") | K65: =COUNTIF(D65:J65,"x") -> 2
A66: B11 | B66: Skills assessment | C66: Precise results with fewer questions | D66: =IF(D19="x","x","") | E66: =IF(E19="x","x","") | F66: =IF(F19="x","x","") | G66: =IF(G19="x","x","") -> x | H66: =IF(H19="x","x","") | I66: =IF(I19="x","x","") | J66: =IF(J19="x","x","") | K66: =COUNTIF(D66:J66,"x") -> 1
A67: B12 | B67: Skills assessment | C67: Students show what they know before their English catches up | D67: =IF(D20="x","x","") -> x | E67: =IF(E20="x","x","") | F67: =IF(F20="x","x","") | G67: =IF(G20="x","x","") -> x | H67: =IF(H20="x","x","") | I67: =IF(I20="x","x","") | J67: =IF(J20="x","x","") | K67: =COUNTIF(D67:J67,"x") -> 2
A68: B13 | B68: Skills assessment | C68: Staff know how much English support a student needs | D68: =IF(D21="x","x","") -> x | E68: =IF(E21="x","x","") | F68: =IF(F21="x","x","") | G68: =IF(G21="x","x","") | H68: =IF(H21="x","x","") -> x | I68: =IF(I21="x","x","") | J68: =IF(J21="x","x","") | K68: =COUNTIF(D68:J68,"x") -> 2
B69: Recommendation & decision support
A70: B14 | B70: Recommendation & decision support | C70: Staff get a clear answer to where a student should begin | D70: =IF(D23="x","x","") -> x | E70: =IF(E23="x","x","") | F70: =IF(F23="x","x","") | G70: =IF(G23="x","x","") -> x | H70: =IF(H23="x","x","") -> x | I70: =IF(I23="x","x","") | J70: =IF(J23="x","x","") | K70: =COUNTIF(D70:J70,"x") -> 3
A71: B15 | B71: Recommendation & decision support | C71: One defensible answer instead of conflicting documents | D71: =IF(D24="x","x","") -> x | E71: =IF(E24="x","x","") | F71: =IF(F24="x","x","") | G71: =IF(G24="x","x","") | H71: =IF(H24="x","x","") | I71: =IF(I24="x","x","") | J71: =IF(J24="x","x","") | K71: =COUNTIF(D71:J71,"x") -> 1
A72: B16 | B72: Recommendation & decision support | C72: Teachers know what to teach first | D72: =IF(D25="x","x","") -> x | E72: =IF(E25="x","x","") | F72: =IF(F25="x","x","") | G72: =IF(G25="x","x","") -> x | H72: =IF(H25="x","x","") -> x | I72: =IF(I25="x","x","") | J72: =IF(J25="x","x","") | K72: =COUNTIF(D72:J72,"x") -> 3
A73: B17 | B73: Recommendation & decision support | C73: Teachers get ready-made material to act on results | D73: =IF(D26="x","x","") | E73: =IF(E26="x","x","") | F73: =IF(F26="x","x","") | G73: =IF(G26="x","x","") -> x | H73: =IF(H26="x","x","") -> x | I73: =IF(I26="x","x","") | J73: =IF(J26="x","x","") | K73: =COUNTIF(D73:J73,"x") -> 2
B74: Family communication
A75: B18 | B75: Family communication | C75: Families understand results without jargon | D75: =IF(D28="x","x","") -> x | E75: =IF(E28="x","x","") | F75: =IF(F28="x","x","") | G75: =IF(G28="x","x","") -> x | H75: =IF(H28="x","x","") | I75: =IF(I28="x","x","") | J75: =IF(J28="x","x","") | K75: =COUNTIF(D75:J75,"x") -> 2
A76: B19 | B76: Family communication | C76: Families can follow and question decisions | D76: =IF(D29="x","x","") -> x | E76: =IF(E29="x","x","") | F76: =IF(F29="x","x","") | G76: =IF(G29="x","x","") -> x | H76: =IF(H29="x","x","") -> x | I76: =IF(I29="x","x","") -> x | J76: =IF(J29="x","x","") | K76: =COUNTIF(D76:J76,"x") -> 4
A77: B20 | B77: Family communication | C77: Families can reply and ask questions in their own language | D77: =IF(D30="x","x","") | E77: =IF(E30="x","x","") | F77: =IF(F30="x","x","") | G77: =IF(G30="x","x","") | H77: =IF(H30="x","x","") | I77: =IF(I30="x","x","") -> x | J77: =IF(J30="x","x","") | K77: =COUNTIF(D77:J77,"x") -> 1
A78: B21 | B78: Family communication | C78: Families get information on the phone they already use | D78: =IF(D31="x","x","") -> x | E78: =IF(E31="x","x","") | F78: =IF(F31="x","x","") | G78: =IF(G31="x","x","") | H78: =IF(H31="x","x","") | I78: =IF(I31="x","x","") -> x | J78: =IF(J31="x","x","") | K78: =COUNTIF(D78:J78,"x") -> 2
A79: B22 | B79: Family communication | C79: Families can help their child between school days | D79: =IF(D32="x","x","") | E79: =IF(E32="x","x","") | F79: =IF(F32="x","x","") | G79: =IF(G32="x","x","") -> x | H79: =IF(H32="x","x","") | I79: =IF(I32="x","x","") -> x | J79: =IF(J32="x","x","") | K79: =COUNTIF(D79:J79,"x") -> 2
A80: B23 | B80: Family communication | C80: Staff can target outreach to hard-to-reach families | D80: =IF(D33="x","x","") | E80: =IF(E33="x","x","") | F80: =IF(F33="x","x","") | G80: =IF(G33="x","x","") | H80: =IF(H33="x","x","") | I80: =IF(I33="x","x","") -> x | J80: =IF(J33="x","x","") | K80: =COUNTIF(D80:J80,"x") -> 1
B81: Case workflow & reporting
A82: B24 | B82: Case workflow & reporting | C82: Staff stop writing from scratch; schools get one clear format | D82: =IF(D35="x","x","") -> x | E82: =IF(E35="x","x","") -> x | F82: =IF(F35="x","x","") -> x | G82: =IF(G35="x","x","") | H82: =IF(H35="x","x","") | I82: =IF(I35="x","x","") | J82: =IF(J35="x","x","") | K82: =COUNTIF(D82:J82,"x") -> 3
A83: B25 | B83: Case workflow & reporting | C83: Staff see where every case stands | D83: =IF(D36="x","x","") -> x | E83: =IF(E36="x","x","") | F83: =IF(F36="x","x","") -> x | G83: =IF(G36="x","x","") | H83: =IF(H36="x","x","") -> x | I83: =IF(I36="x","x","") | J83: =IF(J36="x","x","") | K83: =COUNTIF(D83:J83,"x") -> 3
A84: B26 | B84: Case workflow & reporting | C84: Leaders can report results to funders and boards | D84: =IF(D37="x","x","") -> x | E84: =IF(E37="x","x","") | F84: =IF(F37="x","x","") | G84: =IF(G37="x","x","") -> x | H84: =IF(H37="x","x","") -> x | I84: =IF(I37="x","x","") -> x | J84: =IF(J37="x","x","") | K84: =COUNTIF(D84:J84,"x") -> 4
A85: B27 | B85: Case workflow & reporting | C85: Districts meet English-learner reporting rules | D85: =IF(D38="x","x","") | E85: =IF(E38="x","x","") | F85: =IF(F38="x","x","") | G85: =IF(G38="x","x","") | H85: =IF(H38="x","x","") -> x | I85: =IF(I38="x","x","") | J85: =IF(J38="x","x","") | K85: =COUNTIF(D85:J85,"x") -> 1
A86: B28 | B86: Case workflow & reporting | C86: No double data entry | D86: =IF(D39="x","x","") | E86: =IF(E39="x","x","") | F86: =IF(F39="x","x","") | G86: =IF(G39="x","x","") | H86: =IF(H39="x","x","") -> x | I86: =IF(I39="x","x","") -> x | J86: =IF(J39="x","x","") | K86: =COUNTIF(D86:J86,"x") -> 2
A87: B29 | B87: Case workflow & reporting | C87: Families get answers before the term moves on | D87: =IF(D40="x","x","") -> x | E87: =IF(E40="x","x","") | F87: =IF(F40="x","x","") -> x | G87: =IF(G40="x","x","") | H87: =IF(H40="x","x","") | I87: =IF(I40="x","x","") | J87: =IF(J40="x","x","") | K87: =COUNTIF(D87:J87,"x") -> 2
B88: Trust, privacy & human review
A89: B30 | B89: Trust, privacy & human review | C89: A qualified person stands behind each recommendation | D89: =IF(D42="x","x","") -> x | E89: =IF(E42="x","x","") -> x | F89: =IF(F42="x","x","") -> x | G89: =IF(G42="x","x","") | H89: =IF(H42="x","x","") | I89: =IF(I42="x","x","") | J89: =IF(J42="x","x","") | K89: =COUNTIF(D89:J89,"x") -> 3
A90: B31 | B90: Trust, privacy & human review | C90: Schools and families can trust how data is handled | D90: =IF(D43="x","x","") -> x | E90: =IF(E43="x","x","") | F90: =IF(F43="x","x","") | G90: =IF(G43="x","x","") -> x | H90: =IF(H43="x","x","") -> x | I90: =IF(I43="x","x","") -> x | J90: =IF(J43="x","x","") | K90: =COUNTIF(D90:J90,"x") -> 4
A91: B32 | B91: Trust, privacy & human review | C91: People who fled without documents have a path | D91: =IF(D44="x","x","") -> x | E91: =IF(E44="x","x","") -> x | F91: =IF(F44="x","x","") -> x | G91: =IF(G44="x","x","") | H91: =IF(H44="x","x","") | I91: =IF(I44="x","x","") | J91: =IF(J44="x","x","") | K91: =COUNTIF(D91:J91,"x") -> 3
B92: Access & pricing
A93: B33 | B93: Access & pricing | C93: Buyers can budget without a sales call | D93: =IF(D46="x","x","") -> x | E93: =IF(E46="x","x","") -> x | F93: =IF(F46="x","x","") -> x | G93: =IF(G46="x","x","") | H93: =IF(H46="x","x","") | I93: =IF(I46="x","x","") | J93: =IF(J46="x","x","") | K93: =COUNTIF(D93:J93,"x") -> 3
A94: B34 | B94: Access & pricing | C94: Families never pay to get help | D94: =IF(D47="x","x","") -> x | E94: =IF(E47="x","x","") | F94: =IF(F47="x","x","") -> x | G94: =IF(G47="x","x","") | H94: =IF(H47="x","x","") | I94: =IF(I47="x","x","") -> x | J94: =IF(J47="x","x","") | K94: =COUNTIF(D94:J94,"x") -> 3
A95: B35 | B95: Access & pricing | C95: Fits how affiliates work and budget | D95: =IF(D48="x","x","") -> x | E95: =IF(E48="x","x","") | F95: =IF(F48="x","x","") | G95: =IF(G48="x","x","") | H95: =IF(H48="x","x","") | I95: =IF(I48="x","x","") | J95: =IF(J48="x","x","") | K95: =COUNTIF(D95:J95,"x") -> 1
A96: B36 | B96: Access & pricing | C96: Fits school purchasing and Title III funding | D96: =IF(D49="x","x","") | E96: =IF(E49="x","x","") | F96: =IF(F49="x","x","") | G96: =IF(G49="x","x","") -> x | H96: =IF(H49="x","x","") -> x | I96: =IF(I49="x","x","") -> x | J96: =IF(J49="x","x","") | K96: =COUNTIF(D96:J96,"x") -> 3
C97: Benefits total (of 36) | D97: =COUNTIF(D54:D96,"x") -> 27 | E97: =COUNTIF(E54:E96,"x") -> 10 | F97: =COUNTIF(F54:F96,"x") -> 14 | G97: =COUNTIF(G54:G96,"x") -> 12 | H97: =COUNTIF(H54:H96,"x") -> 11 | I97: =COUNTIF(I54:I96,"x") -> 10 | J97: =COUNTIF(J54:J96,"x") -> 1
A99: Legend
A100: x Offered. Competitors: found on the competitor's own website (see Sources). Paso: planned MVP feature, not a live product.
A101: Blank Not offered, or not verified. Unverified items are listed on the Sources sheet.
A102: Teal shading in a row Only Paso plans this feature among all seven columns.
A103: Status quo Baseline from the team's interview, not one of the five competitors.
...

Sheet Competitor Profiles
A1: Competitor Profiles
A2: Five competitors plus the manual baseline. Facts come from each competitor's own website (see Sources), accessed 2026-10-05.
A4: Competitor | B4: Type | C4: Why it's included | D4: Description | E4: Primary customer | F4: Business model or pricing | G4: Strength | H4: Gap versus Paso's customer | I4: Source URL | J4: Date accessed
A5: World Education Services (WES) | B5: Direct | C5: Evaluates foreign high-school records course by course and runs a program for refugees without documents: the closest substitute for Paso's record mapping. | D5: WES evaluates high school and post-secondary credentials from more than 200 countries and issues Document-by-Document or Course-by-Course reports with U.S. or Canadian equivalencies. Its Gateway Program evaluates eligible displaced people who cannot obtain official documents, through referral partner organizations. | E5: Individuals applying to schools, employers, licensing bodies and immigration authorities | F5: Fee per report: Course-by-Course from $186; Document-by-Document from $118 (3% increase announced from Jan 1, 2026) | G5: Widely accepted reports; verifies documents with issuing institutions; dedicated refugee program | H5: Needs official documents and certified translations outside Gateway; Course-by-Course takes about 2 weeks after verification; gives a U.S. equivalency, not a local grade and course plan; Gateway requires completed high school or college study, so students still in school fall outside it. | I5: https://www.wes.org/evaluations/ | J5: 2026-10-05
A6: Educational Credential Evaluators (ECE) | B6: Direct | C6: Same evaluation model as WES, plus AI transcript extraction and free reports for refugees through nonprofits (ECE Aid). | D6: ECE is a nonprofit that evaluates foreign academic credentials, including Course by Course reports covering high school and university study with GPA. It adds AI-extracted transcript summaries (MyDocs Academic Profile) for institutions and free reports for refugees through ECE Aid vouchers. | E6: Individuals and U.S. and Canadian institutions | F6: Fee per report: General with GPA $180; Course by Course $199; 5-business-day rush $90; Translation Waiver $85 | G6: Fast (3-5 business days average once documents are complete); AI extraction; nonprofit voucher channel | H6: Requires official documents and translations (or a waiver fee); produces an equivalency report. We found no skills check, local course match or family-facing plan on its site. | I6: https://www.ece.org/ECE/Credential-Evaluations/US-Institutions/Services-and-Fees | J6: 2026-10-05
A7: i-Ready (Curriculum Associates) | B7: Indirect | C7: The diagnostic many schools already use to find a student's level; expands the team's Assignment 2. | D7: i-Ready Inform (formerly i-Ready Diagnostic) is an adaptive reading and math assessment for grades K-12 that places students relative to grade level and links results to instruction. Spanish versions cover math K-12 and reading K-8; Personalized Instruction adds online lessons for grades K-8. | E7: Schools and districts | F7: Not published; through a sales representative; Personalized Instruction needs at least 150 assessment licenses | G7: Trusted adaptive assessment, educator and family reports, Spanish options | H7: Measures skills, not prior records or credits; home-language options are Spanish only; sold to schools, not to nonprofits that serve families before enrollment. | I7: https://www.curriculumassociates.com/programs/i-ready-assessment/diagnostic | J7: 2026-10-05
A8: Ellevation | B8: Indirect | C8: The English-learner platform districts use for identification, placement and family communication; part of Curriculum Associates since 2021. | D8: Ellevation is a platform for district English-learner programs: student profiles, identification and placement workflows, monitoring forms, compliance reports and dashboards. It adds Benchmark ELD assessments, classroom strategies and family communication in home languages. | E8: District English-learner programs | F8: Not published; priced by number of English learners; most districts fund it with Title III | G8: Owns the district's English-learner workflow, with SIS integration and SOC 2 Type 2 security | H8: Starts after enrollment, inside the district; we found no evaluation of foreign records or credits; not sold to nonprofits. | I8: https://ellevationeducation.com/product/ellevation-platform | J8: 2026-10-05
A9: TalkingPoints | B9: Indirect | C9: The tool schools use to talk with multilingual families; competes for the job of making sure families understand. | D9: TalkingPoints is a nonprofit family-engagement platform that auto-translates two-way messages between school staff and families in more than 150 languages, using human translators and AI. Families can receive texts with no app on paid plans; schools get analytics, attendance tools and SIS syncing. | E9: Teachers (free); schools and districts (paid) | F9: Free for teachers; school and district pricing not published | G9: Reaches families in their language on any phone, at scale | H9: Carries messages but does not evaluate records, check skills or recommend a starting point. | I9: https://talkingpts.org/teachers/ | J9: 2026-10-05
A10: Status quo (baseline, not a competitor) | B10: Baseline | C10: What case managers do today, from the team's interview. | D10: Case managers piece together records with informal Google searches or unstandardized translation tools and write custom letters from scratch for every case. | E10: Resettlement affiliate staff | F10: No fee; paid in staff time | G10: Free and flexible | H10: One Arabic transcript took over five hours across three weeks; parents leave placement meetings confused; staff delay recommendations for fear of a wrong placement. | I10: Team interview (Part 2) | J10: Sept 2026

Sheet Positioning
A1: Positioning: strategy canvas
A2: Scores 0-3 per factor = how many of the factor's three matrix features each product has (formulas link to the matrix).
A4: Factor | B4: Scored from these matrix features | C4: Paso (planned MVP) | D4: WES | E4: ECE | F4: i-Ready | G4: Ellevation | H4: TalkingPoints | I4: Status quo (baseline)
A5: Works from imperfect records | B5: F1 Receive records digitally; F2 Accept copies when official records are missing; F3 Translate records into English | C5: =('Features & Benefits Matrix'!D7="x")+('Features & Benefits Matrix'!D8="x")+('Features & Benefits Matrix'!D9="x") -> 3 | D5: =('Features & Benefits Matrix'!E7="x")+('Features & Benefits Matrix'!E8="x")+('Features & Benefits Matrix'!E9="x") -> 2 | E5: =('Features & Benefits Matrix'!F7="x")+('Features & Benefits Matrix'!F8="x")+('Features & Benefits Matrix'!F9="x") -> 2 | F5: =('Features & Benefits Matrix'!G7="x")+('Features & Benefits Matrix'!G8="x")+('Features & Benefits Matrix'!G9="x") -> 0 | G5: =('Features & Benefits Matrix'!H7="x")+('Features & Benefits Matrix'!H8="x")+('Features & Benefits Matrix'!H9="x") -> 0 | H5: =('Features & Benefits Matrix'!I7="x")+('Features & Benefits Matrix'!I8="x")+('Features & Benefits Matrix'!I9="x") -> 0 | I5: =('Features & Benefits Matrix'!J7="x")+('Features & Benefits Matrix'!J8="x")+('Features & Benefits Matrix'!J9="x") -> 1
A6: Course and credit evidence | B6: F7 Evaluate course by course; F8 Convert grades and credits to U.S. terms; F9 Match to local grade level and courses | C6: =('Features & Benefits Matrix'!D14="x")+('Features & Benefits Matrix'!D15="x")+('Features & Benefits Matrix'!D16="x") -> 3 | D6: =('Features & Benefits Matrix'!E14="x")+('Features & Benefits Matrix'!E15="x")+('Features & Benefits Matrix'!E16="x") -> 2 | E6: =('Features & Benefits Matrix'!F14="x")+('Features & Benefits Matrix'!F15="x")+('Features & Benefits Matrix'!F16="x") -> 2 | F6: =('Features & Benefits Matrix'!G14="x")+('Features & Benefits Matrix'!G15="x")+('Features & Benefits Matrix'!G16="x") -> 0 | G6: =('Features & Benefits Matrix'!H14="x")+('Features & Benefits Matrix'!H15="x")+('Features & Benefits Matrix'!H16="x") -> 0 | H6: =('Features & Benefits Matrix'!I14="x")+('Features & Benefits Matrix'!I15="x")+('Features & Benefits Matrix'!I16="x") -> 0 | I6: =('Features & Benefits Matrix'!J14="x")+('Features & Benefits Matrix'!J15="x")+('Features & Benefits Matrix'!J16="x") -> 0
A7: Skills check | B7: F10 Assess reading and math; F12 Test in the student's home language; F13 Measure English proficiency | C7: =('Features & Benefits Matrix'!D18="x")+('Features & Benefits Matrix'!D20="x")+('Features & Benefits Matrix'!D21="x") -> 3 | D7: =('Features & Benefits Matrix'!E18="x")+('Features & Benefits Matrix'!E20="x")+('Features & Benefits Matrix'!E21="x") -> 0 | E7: =('Features & Benefits Matrix'!F18="x")+('Features & Benefits Matrix'!F20="x")+('Features & Benefits Matrix'!F21="x") -> 0 | F7: =('Features & Benefits Matrix'!G18="x")+('Features & Benefits Matrix'!G20="x")+('Features & Benefits Matrix'!G21="x") -> 2 | G7: =('Features & Benefits Matrix'!H18="x")+('Features & Benefits Matrix'!H20="x")+('Features & Benefits Matrix'!H21="x") -> 1 | H7: =('Features & Benefits Matrix'!I18="x")+('Features & Benefits Matrix'!I20="x")+('Features & Benefits Matrix'!I21="x") -> 0 | I7: =('Features & Benefits Matrix'!J18="x")+('Features & Benefits Matrix'!J20="x")+('Features & Benefits Matrix'!J21="x") -> 0
A8: Placement recommendation | B8: F14 Recommend a starting point; F15 Combine records and skills results in one recommendation; F16 Suggest next instructional steps | C8: =('Features & Benefits Matrix'!D23="x")+('Features & Benefits Matrix'!D24="x")+('Features & Benefits Matrix'!D25="x") -> 3 | D8: =('Features & Benefits Matrix'!E23="x")+('Features & Benefits Matrix'!E24="x")+('Features & Benefits Matrix'!E25="x") -> 0 | E8: =('Features & Benefits Matrix'!F23="x")+('Features & Benefits Matrix'!F24="x")+('Features & Benefits Matrix'!F25="x") -> 0 | F8: =('Features & Benefits Matrix'!G23="x")+('Features & Benefits Matrix'!G24="x")+('Features & Benefits Matrix'!G25="x") -> 2 | G8: =('Features & Benefits Matrix'!H23="x")+('Features & Benefits Matrix'!H24="x")+('Features & Benefits Matrix'!H25="x") -> 2 | H8: =('Features & Benefits Matrix'!I23="x")+('Features & Benefits Matrix'!I24="x")+('Features & Benefits Matrix'!I25="x") -> 0 | I8: =('Features & Benefits Matrix'!J23="x")+('Features & Benefits Matrix'!J24="x")+('Features & Benefits Matrix'!J25="x") -> 0
A9: Family understanding | B9: F18 Give families a plain-language report; F19 Communicate in the family's language; F21 Reach families without a new app | C9: =('Features & Benefits Matrix'!D28="x")+('Features & Benefits Matrix'!D29="x")+('Features & Benefits Matrix'!D31="x") -> 3 | D9: =('Features & Benefits Matrix'!E28="x")+('Features & Benefits Matrix'!E29="x")+('Features & Benefits Matrix'!E31="x") -> 0 | E9: =('Features & Benefits Matrix'!F28="x")+('Features & Benefits Matrix'!F29="x")+('Features & Benefits Matrix'!F31="x") -> 0 | F9: =('Features & Benefits Matrix'!G28="x")+('Features & Benefits Matrix'!G29="x")+('Features & Benefits Matrix'!G31="x") -> 2 | G9: =('Features & Benefits Matrix'!H28="x")+('Features & Benefits Matrix'!H29="x")+('Features & Benefits Matrix'!H31="x") -> 1 | H9: =('Features & Benefits Matrix'!I28="x")+('Features & Benefits Matrix'!I29="x")+('Features & Benefits Matrix'!I31="x") -> 2 | I9: =('Features & Benefits Matrix'!J28="x")+('Features & Benefits Matrix'!J29="x")+('Features & Benefits Matrix'!J31="x") -> 0
A10: Speed and standard output | B10: F24 Use a standard report or letter; F25 Track each case online; F29 Return results within one week | C10: =('Features & Benefits Matrix'!D35="x")+('Features & Benefits Matrix'!D36="x")+('Features & Benefits Matrix'!D40="x") -> 3 | D10: =('Features & Benefits Matrix'!E35="x")+('Features & Benefits Matrix'!E36="x")+('Features & Benefits Matrix'!E40="x") -> 1 | E10: =('Features & Benefits Matrix'!F35="x")+('Features & Benefits Matrix'!F36="x")+('Features & Benefits Matrix'!F40="x") -> 3 | F10: =('Features & Benefits Matrix'!G35="x")+('Features & Benefits Matrix'!G36="x")+('Features & Benefits Matrix'!G40="x") -> 0 | G10: =('Features & Benefits Matrix'!H35="x")+('Features & Benefits Matrix'!H36="x")+('Features & Benefits Matrix'!H40="x") -> 1 | H10: =('Features & Benefits Matrix'!I35="x")+('Features & Benefits Matrix'!I36="x")+('Features & Benefits Matrix'!I40="x") -> 0 | I10: =('Features & Benefits Matrix'!J35="x")+('Features & Benefits Matrix'!J36="x")+('Features & Benefits Matrix'!J40="x") -> 0
A11: Trust and safeguards | B11: F5 Verify authenticity with the issuing school; F30 Have a trained person review every result; F31 Publish student-data privacy commitments | C11: =('Features & Benefits Matrix'!D11="x")+('Features & Benefits Matrix'!D42="x")+('Features & Benefits Matrix'!D43="x") -> 2 | D11: =('Features & Benefits Matrix'!E11="x")+('Features & Benefits Matrix'!E42="x")+('Features & Benefits Matrix'!E43="x") -> 2 | E11: =('Features & Benefits Matrix'!F11="x")+('Features & Benefits Matrix'!F42="x")+('Features & Benefits Matrix'!F43="x") -> 2 | F11: =('Features & Benefits Matrix'!G11="x")+('Features & Benefits Matrix'!G42="x")+('Features & Benefits Matrix'!G43="x") -> 1 | G11: =('Features & Benefits Matrix'!H11="x")+('Features & Benefits Matrix'!H42="x")+('Features & Benefits Matrix'!H43="x") -> 1 | H11: =('Features & Benefits Matrix'!I11="x")+('Features & Benefits Matrix'!I42="x")+('Features & Benefits Matrix'!I43="x") -> 1 | I11: =('Features & Benefits Matrix'!J11="x")+('Features & Benefits Matrix'!J42="x")+('Features & Benefits Matrix'!J43="x") -> 0
A12: Fit for nonprofit buyers | B12: F32 Serve refugees and displaced people; F34 Free for families; F35 Sold to resettlement nonprofits | C12: =('Features & Benefits Matrix'!D44="x")+('Features & Benefits Matrix'!D47="x")+('Features & Benefits Matrix'!D48="x") -> 3 | D12: =('Features & Benefits Matrix'!E44="x")+('Features & Benefits Matrix'!E47="x")+('Features & Benefits Matrix'!E48="x") -> 1 | E12: =('Features & Benefits Matrix'!F44="x")+('Features & Benefits Matrix'!F47="x")+('Features & Benefits Matrix'!F48="x") -> 2 | F12: =('Features & Benefits Matrix'!G44="x")+('Features & Benefits Matrix'!G47="x")+('Features & Benefits Matrix'!G48="x") -> 0 | G12: =('Features & Benefits Matrix'!H44="x")+('Features & Benefits Matrix'!H47="x")+('Features & Benefits Matrix'!H48="x") -> 0 | H12: =('Features & Benefits Matrix'!I44="x")+('Features & Benefits Matrix'!I47="x")+('Features & Benefits Matrix'!I48="x") -> 1 | I12: =('Features & Benefits Matrix'!J44="x")+('Features & Benefits Matrix'!J47="x")+('Features & Benefits Matrix'!J48="x") -> 0
A14: Rubric: 0 = none of the three features; 3 = all three. Competitor marks are verified on their own websites; Paso's are planned.

Sheet Sources
A1: Sources
A2: Every competitor mark traces to a source ID here. Pages were found by searches limited to each competitor's own domain; this environment could not open them directly, so click to confirm before submitting.
A4: ID | B4: Product | C4: Claim used | D4: Matrix features | E4: URL | F4: Date accessed | G4: Status
A5: S1 | B5: WES | C5: Course-by-Course report: equivalency for each credential, each course analyzed, credits and grades converted, GPA calculated | D5: F7, F8, F9 | E5: https://www.wes.org/resource-library/blog/credential-advice/why-upgrade-to-cxc-report/ | F5: 2026-10-05 | G5: Verified: competitor's own website (found by a search limited to its domain; open the link to confirm)
A6: S2 | B6: WES | C6: Evaluates high school and post-secondary credentials from more than 200 countries | D6: F6 | E6: https://www.wes.org/credential-evaluation-for-employment/ | F6: 2026-10-05 | G6: Verified: competitor's own website (found by a search limited to its domain; open the link to confirm)
A7: S3 | B7: WES | C7: Fees: Course-by-Course from $186 USD; Document-by-Document from $118 USD; 3% increase announced from Jan 1, 2026 | D7: F33 | E7: https://www.wes.org/evaluations/ | F7: 2026-10-05 | G7: Verified: competitor's own website (found by a search limited to its domain; open the link to confirm)
A8: S4 | B8: WES | C8: Processing: 2-3 business days to process documents; Document-by-Document about 1 week (up to 2), Course-by-Course about 2 weeks (up to 4) after documents are verified | D8: F29 | E8: https://www.wes.org/current-processing/ | F8: 2026-10-05 | G8: Verified: competitor's own website (found by a search limited to its domain; open the link to confirm)
A9: S5 | B9: WES | C9: Official documents come from the issuing institution; WES verifies documents with issuing institutions | D9: F5 | E9: https://www.wes.org/resource-library/blog/credential-advice/verification-status/ | F9: 2026-10-05 | G9: Verified: competitor's own website (found by a search limited to its domain; open the link to confirm)
A10: S6 | B10: WES | C10: Requires official word-for-word English translations; does not offer translation; WES evaluators verify translations during evaluation | D10: F3, F30 | E10: https://www.wes.org/resource-library/blog/credential-advice/understanding-required-documents-for-credential-evaluation/ | F10: 2026-10-05 | G10: Verified: competitor's own website (found by a search limited to its domain; open the link to confirm)
A11: S7 | B11: WES | C11: Accepts electronic academic records through approved means | D11: F1 | E11: https://www.wes.org/send-electronic-academic-records/ | F11: 2026-10-05 | G11: Verified: competitor's own website (found by a search limited to its domain; open the link to confirm)
A12: S8 | B12: WES | C12: Gateway Program: evaluates refugees and displaced people who cannot obtain official documents (listed countries; completed high school or college study; copies required); referral partner organizations submit cases | D12: F2, F32, F35 | E12: https://www.wes.org/social-impact/programming/wes-gateway-program/ | F12: 2026-10-05 | G12: Verified: competitor's own website (found by a search limited to its domain; open the link to confirm)
A13: S10 | B13: WES | C13: Two standard report types: Document-by-Document and Course-by-Course | D13: F24 | E13: https://www.wes.org/resource-library/blog/credential-advice/the-difference-between-document-by-document-and-course-by-course-credential-evaluation-reports/ | F13: 2026-10-05 | G13: Verified: competitor's own website (found by a search limited to its domain; open the link to confirm)
A14: S11 | B14: ECE | C14: Report types and fees: Course by Course (high school and university courses, credits, grades, GPA), General, General with Grade Average; General with GPA $180, Course by Course $199, 5-business-day rush $90 | D14: F6, F7, F8, F9, F24, F33 | E14: https://www.ece.org/ECE/Credential-Evaluations/US-Institutions/Services-and-Fees | F14: 2026-10-05 | G14: Verified: competitor's own website (found by a search limited to its domain; open the link to confirm)
A15: S12 | B15: ECE | C15: Processing averages 3-5 business days after all required information is received | D15: F29 | E15: https://www.ece.org/ECE/Credential-Evaluations/Individual-FAQs | F15: 2026-10-05 | G15: Verified: competitor's own website (found by a search limited to its domain; open the link to confirm)
... A48: S46 | B48: Paso | C48: Team document (Parts 1-3): Paso design, customers and targets (~4 to 2 staff hours; ~2 weeks to 3 business days; $30 per student, hypothesis H3) | D48: Profiles | E48: The Jackson Krewe Assignments (team document) | F48: Sept 2026 | G48: Team document: design and targets (hypotheses, not results)
A50: Unverified or not found (left blank in the matrix)
A51: U1 | B51: i-Ready | C51: Integration with student information systems: not found on the pages searched.
A52: U2 | B52: Ellevation | C52: Two-way translated messaging with families: not stated on the Family Communication page found.
A53: U3 | B53: WES | C53: Gateway Program fees and whether it accepts students still in secondary school beyond the stated eligibility: not found.
A54: U4 | B54: TalkingPoints | C54: School and district prices: not published.
A55: U5 | B55: All competitors | C55: Whether they ask about immigration status: not checked; Paso's 'never ask' commitment is compared only as a Paso design choice.
A56: U6 | B56: Team statistic | C56: Boston 16% vs Springfield 64% (Mantil et al., 2026): not independently verified; the 38-point adjusted gap matches Brown University and Education Week coverage. Not used in this workbook.
